pynotice/__init__.py
pynotice/demo/__init__.py
pynotice/demo/demo.txt
pynotice/demo/main.py
pynotice/demo/test.txt
pynotice/mail/__init__.py
pynotice/mail/notice.py
pynotice/mail/utils.py
pynotice/sound/__init__.py
pynotice/sound/notice.py
pynotice/sound/utils.py
pynotice/sound/resource/__init__.py
pynotice/sound/resource/error.wav
pynotice/sound/resource/success.wav
pynotice-0.0.2.dist-info/LICENSE
pynotice-0.0.2.dist-info/METADATA
pynotice-0.0.2.dist-info/WHEEL
pynotice-0.0.2.dist-info/top_level.txt
pynotice-0.0.2.dist-info/RECORD
