Metadata-Version: 2.1
Name: pynotice
Version: 0.0.2
Summary: notice by sound or email
Home-page: https://github.com/shaoeric/pynotice
Author: shaoeric
Author-email: shaoeric@foxmail.com
License: UNKNOWN
Platform: UNKNOWN
Classifier: Programming Language :: Python :: 3
Classifier: License :: OSI Approved :: MIT License
Classifier: Operating System :: OS Independent
Requires-Dist: zmail (==0.2.5)
